CHANGELOG.md
bootloader/__init__.py
bootloader/utils/__init__.py
bootloader/utils/cli/__init__.py
bootloader/utils/cli/converter.py
bootloader/utils/maya/__init__.py
bootloader/utils/maya/converter.py
bootloader/utils/maya/playblast.py
bootloader_maya_utils_library-1.0.0.dist-info/LICENSE
bootloader_maya_utils_library-1.0.0.dist-info/WHEEL
bootloader_maya_utils_library-1.0.0.dist-info/entry_points.txt
bootloader_maya_utils_library-1.0.0.dist-info/METADATA
bootloader_maya_utils_library-1.0.0.dist-info/RECORD
